PythonQianghuaXuexiShiyongZhinanChuyi/README.md
PythonQianghuaXuexiShiyongZhinanChuyi/__init__.py
PythonQianghuaXuexiShiyongZhinanChuyi/__main__.py
PythonQianghuaXuexiShiyongZhinanChuyi/file.epub
PythonQianghuaXuexiShiyongZhinanChuyi/index.html
PythonQianghuaXuexiShiyongZhinanChuyi/css/__init__.py
PythonQianghuaXuexiShiyongZhinanChuyi/css/annotations.css
PythonQianghuaXuexiShiyongZhinanChuyi/css/main.css
PythonQianghuaXuexiShiyongZhinanChuyi/css/normalize.css
PythonQianghuaXuexiShiyongZhinanChuyi/css/popup.css
PythonQianghuaXuexiShiyongZhinanChuyi/font/__init__.py
PythonQianghuaXuexiShiyongZhinanChuyi/font/fontello.eot
PythonQianghuaXuexiShiyongZhinanChuyi/font/fontello.svg
PythonQianghuaXuexiShiyongZhinanChuyi/font/fontello.ttf
PythonQianghuaXuexiShiyongZhinanChuyi/font/fontello.woff
PythonQianghuaXuexiShiyongZhinanChuyi/img/__init__.py
PythonQianghuaXuexiShiyongZhinanChuyi/img/annotator-glyph-sprite.png
PythonQianghuaXuexiShiyongZhinanChuyi/img/annotator-icon-sprite.png
PythonQianghuaXuexiShiyongZhinanChuyi/img/apple-touch-icon.png
PythonQianghuaXuexiShiyongZhinanChuyi/img/cancelfullscreen.png
PythonQianghuaXuexiShiyongZhinanChuyi/img/close.png
PythonQianghuaXuexiShiyongZhinanChuyi/img/fullscreen.png
PythonQianghuaXuexiShiyongZhinanChuyi/img/loader.gif
PythonQianghuaXuexiShiyongZhinanChuyi/img/menu-icon.png
PythonQianghuaXuexiShiyongZhinanChuyi/img/save.png
PythonQianghuaXuexiShiyongZhinanChuyi/img/saved.png
PythonQianghuaXuexiShiyongZhinanChuyi/img/settings-s.png
PythonQianghuaXuexiShiyongZhinanChuyi/img/settings.png
PythonQianghuaXuexiShiyongZhinanChuyi/img/star.png
PythonQianghuaXuexiShiyongZhinanChuyi/js/__init__.py
PythonQianghuaXuexiShiyongZhinanChuyi/js/epub.js
PythonQianghuaXuexiShiyongZhinanChuyi/js/epub.min.js
PythonQianghuaXuexiShiyongZhinanChuyi/js/epub.min.map
PythonQianghuaXuexiShiyongZhinanChuyi/js/hooks.min.js
PythonQianghuaXuexiShiyongZhinanChuyi/js/hooks.min.map
PythonQianghuaXuexiShiyongZhinanChuyi/js/reader.js
python_qianghua_xuexi_shiyong_zhinan_chuyi-2024.3.6.0.dist-info/METADATA
python_qianghua_xuexi_shiyong_zhinan_chuyi-2024.3.6.0.dist-info/WHEEL
python_qianghua_xuexi_shiyong_zhinan_chuyi-2024.3.6.0.dist-info/entry_points.txt
python_qianghua_xuexi_shiyong_zhinan_chuyi-2024.3.6.0.dist-info/top_level.txt
python_qianghua_xuexi_shiyong_zhinan_chuyi-2024.3.6.0.dist-info/RECORD
